{
    "name": "L_1_1",
    "id": "11007",
    "rule": "RuleOri",
    "mode": "Normal",
    "pass_limit": 999,
    "lead_limit": 999,
    "pass_request": 0,
    "lead_request": 0,
    "landlord": "YOU",
    "number": 2,
    "players": [
        "YOU",
        "Robot"
    ],
    "cards": [
        [
            "club-6",
            "club-6",
            "club-6",
            "club-8",
            "club-8",
            "club-8",
            "diamond-10",
            "diamond-10",
            "diamond-10",
            "heart-Q",
            "heart-Q",
            "heart-Q"
        ],
        [
            "spade-J",
            "spade-K",
            "spade-K",
            "spade-Q",
            "spade-Q",
            "spade-Q"
        ]
    ]
}